con_duct/__init__.py
con_duct/_version.py
con_duct/cli.py
con_duct/duct_main.py
con_duct/json_utils.py
con_duct/ls.py
con_duct/plot.py
con_duct/pprint_json.py
con_duct/py.typed
con_duct/utils.py
con_duct-0.19.0.dist-info/licenses/LICENSE
con_duct-0.19.0.dist-info/METADATA
con_duct-0.19.0.dist-info/WHEEL
con_duct-0.19.0.dist-info/entry_points.txt
con_duct-0.19.0.dist-info/top_level.txt
con_duct-0.19.0.dist-info/RECORD
