Metadata-Version: 2.4
Name: con-duct
Version: 0.19.0
Summary: Runs a not-so-simple command and collects resource usage metrics
Home-page: https://github.com/con/duct/
Author: Austin Macdonald
Author-email: austin@dartmouth.edu
License: MIT
Project-URL: Source Code, https://github.com/con/duct/
Project-URL: Bug Tracker, https://github.com/con/duct/issues
Keywords: command-line,cpu,memory,metrics,output-capture,provenance,time,usage
Classifier: Development Status :: 3 - Alpha
Classifier: Programming Language :: Python :: 3 :: Only
Classifier: Programming Language :: Python :: 3
Classifier: Programming Language :: Python :: 3.10
Classifier: Programming Language :: Python :: 3.11
Classifier: Programming Language :: Python :: 3.12
Classifier: Programming Language :: Python :: 3.13
Classifier: Programming Language :: Python :: 3.14
Classifier: Programming Language :: Python :: Implementation :: CPython
Classifier: Programming Language :: Python :: Implementation :: PyPy
Classifier: License :: OSI Approved :: MIT License
Classifier: Environment :: Console
Classifier: Intended Audience :: Developers
Classifier: Intended Audience :: Information Technology
Classifier: Intended Audience :: Science/Research
Classifier: Intended Audience :: System Administrators
Classifier: Topic :: System :: Systems Administration
Classifier: Operating System :: Unix
Classifier: Operating System :: MacOS
Requires-Python: >=3.10
License-File: LICENSE
Provides-Extra: all
Requires-Dist: matplotlib>=3.5; extra == "all"
Requires-Dist: PyYAML>=6.0; extra == "all"
Requires-Dist: pyout>=0.8; extra == "all"
Requires-Dist: rpds-py<0.28.0; implementation_name == "pypy" and extra == "all"
Requires-Dist: python-dotenv>=0.19; extra == "all"
Dynamic: license-file
